{"working_dir":null,"default_chunk_options":{"echo":true},"chunk_definitions":[{"row":10,"row_count":1,"visible":true,"expansion_state":0,"options":{"engine":"r","label":"setup","include":false,"dev":"png"},"document_id":"43F61737","chunk_id":"csetup_chunk","chunk_label":"setup"},{"row":107,"row_count":1,"visible":true,"expansion_state":0,"options":{"engine":"r","label":"unnamed-chunk-227","dev":"png"},"document_id":"43F61737","chunk_id":"c6m94n3qf9dew","chunk_label":"unnamed-chunk-13"},{"row":327,"row_count":1,"visible":true,"expansion_state":0,"options":{"engine":"r","label":"unnamed-chunk-145","dev":"png"},"document_id":"43F61737","chunk_id":"ca4qkew0lfwkz","chunk_label":"unnamed-chunk-25"},{"row":334,"row_count":1,"visible":true,"expansion_state":0,"options":{"engine":"r","label":"unnamed-chunk-175","dev":"png"},"document_id":"43F61737","chunk_id":"cwcqr1iu2ff5j","chunk_label":"unnamed-chunk-27"},{"row":342,"row_count":1,"visible":true,"expansion_state":0,"options":{"engine":"r","label":"unnamed-chunk-187","dev":"png"},"document_id":"43F61737","chunk_id":"c27oamabg12t0","chunk_label":"unnamed-chunk-29"},{"row":348,"row_count":1,"visible":true,"expansion_state":0,"options":{"engine":"r","label":"unnamed-chunk-185","dev":"png"},"document_id":"43F61737","chunk_id":"coi53ffce8g40","chunk_label":"unnamed-chunk-30"},{"row":356,"row_count":1,"visible":true,"expansion_state":0,"options":{"engine":"r","label":"unnamed-chunk-196","dev":"png"},"document_id":"43F61737","chunk_id":"ce9s9066jil8g","chunk_label":"unnamed-chunk-31"},{"row":360,"row_count":1,"visible":true,"expansion_state":0,"options":{"engine":"r","label":"unnamed-chunk-197","dev":"png"},"document_id":"43F61737","chunk_id":"cwhlj5ffp9xsg","chunk_label":"unnamed-chunk-32"},{"row":367,"row_count":1,"visible":true,"expansion_state":0,"options":{"engine":"r","label":"unnamed-chunk-168","dev":"png"},"document_id":"43F61737","chunk_id":"ccf2muuwn0rsw","chunk_label":"unnamed-chunk-33"},{"row":383,"row_count":1,"visible":true,"expansion_state":0,"options":{"engine":"r","label":"unnamed-chunk-147","dev":"png"},"document_id":"43F61737","chunk_id":"cxud78shqgvwu","chunk_label":"unnamed-chunk-36"},{"row":387,"row_count":1,"visible":true,"expansion_state":0,"options":{"engine":"r","label":"unnamed-chunk-169","dev":"png"},"document_id":"43F61737","chunk_id":"czgl1cxdxesip","chunk_label":"unnamed-chunk-37"},{"row":395,"row_count":1,"visible":true,"expansion_state":0,"options":{"engine":"r","label":"unnamed-chunk-170","dev":"png"},"document_id":"43F61737","chunk_id":"c0y35kprhej34","chunk_label":"unnamed-chunk-39"},{"row":402,"row_count":1,"visible":true,"expansion_state":0,"options":{"engine":"r","label":"unnamed-chunk-152","dev":"png"},"document_id":"43F61737","chunk_id":"cj76oahsq2jvz","chunk_label":"unnamed-chunk-40"}],"doc_write_time":1710292278}